msys_opt/__init__.py
msys_opt/registration.py
msys_opt/core/__init__.py
msys_opt/core/np_parser.py
msys_opt/core/optimizer.py
msys_opt/core/optimizable/__init__.py
msys_opt/core/optimizable/generator.py
msys_opt/core/optimizable/input.py
msys_opt/core/optimizable/optimizable.py
msys_opt/core/optimizable/output.py
msys_opt/core/optimizable/type.py
msys_opt/modules/__init__.py
msys_opt/modules/math.py
msys_opt/modules/processor.py
msys_opt/modules/sql.py
msys_opt/optimizer/__init__.py
msys_opt/server/__init__.py
msys_opt/types/__init__.py
msys_opt/types/vector.py
msys_opt-0.0.1.dist-info/LICENSE
msys_opt-0.0.1.dist-info/METADATA
msys_opt-0.0.1.dist-info/WHEEL
msys_opt-0.0.1.dist-info/entry_points.txt
msys_opt-0.0.1.dist-info/top_level.txt
msys_opt-0.0.1.dist-info/RECORD
